oHySEM/__init__.py
oHySEM/oHySEM.mapbox_token
oHySEM/oHySEM.py
oHySEM/oHySEM_API.py
oHySEM/VPP1/oH_Data_Duration_VPP1.csv
oHySEM/VPP1/oH_Data_ElectricityCost_VPP1.csv
oHySEM/VPP1/oH_Data_ElectricityDemand_VPP1.csv
oHySEM/VPP1/oH_Data_ElectricityNetwork_VPP1.csv
oHySEM/VPP1/oH_Data_ElectricityPrice_VPP1.csv
oHySEM/VPP1/oH_Data_Generation_VPP1.csv
oHySEM/VPP1/oH_Data_HydrogenCost_VPP1.csv
oHySEM/VPP1/oH_Data_HydrogenDemand_VPP1.csv
oHySEM/VPP1/oH_Data_HydrogenNetwork_VPP1.csv
oHySEM/VPP1/oH_Data_HydrogenPrice_VPP1.csv
oHySEM/VPP1/oH_Data_NodeLocation_VPP1.csv
oHySEM/VPP1/oH_Data_OperatingReserveActivation_VPP1.csv
oHySEM/VPP1/oH_Data_OperatingReservePrice_VPP1.csv
oHySEM/VPP1/oH_Data_OperatingReserveRequire_VPP1.csv
oHySEM/VPP1/oH_Data_Option_VPP1.csv
oHySEM/VPP1/oH_Data_Parameter_VPP1.csv
oHySEM/VPP1/oH_Data_Period_VPP1.csv
oHySEM/VPP1/oH_Data_Scenario_VPP1.csv
oHySEM/VPP1/oH_Data_Tariff_VPP1.csv
oHySEM/VPP1/oH_Data_VarMaxConsumption_VPP1.csv
oHySEM/VPP1/oH_Data_VarMaxEmissionCost_VPP1.csv
oHySEM/VPP1/oH_Data_VarMaxEnergy_VPP1.csv
oHySEM/VPP1/oH_Data_VarMaxFuelCost_VPP1.csv
oHySEM/VPP1/oH_Data_VarMaxGeneration_VPP1.csv
oHySEM/VPP1/oH_Data_VarMaxInflows_VPP1.csv
oHySEM/VPP1/oH_Data_VarMaxOutflows_VPP1.csv
oHySEM/VPP1/oH_Data_VarMaxStorage_VPP1.csv
oHySEM/VPP1/oH_Data_VarMinConsumption_VPP1.csv
oHySEM/VPP1/oH_Data_VarMinEmissionCost_VPP1.csv
oHySEM/VPP1/oH_Data_VarMinEnergy_VPP1.csv
oHySEM/VPP1/oH_Data_VarMinFuelCost_VPP1.csv
oHySEM/VPP1/oH_Data_VarMinGeneration_VPP1.csv
oHySEM/VPP1/oH_Data_VarMinInflows_VPP1.csv
oHySEM/VPP1/oH_Data_VarMinOutflows_VPP1.csv
oHySEM/VPP1/oH_Data_VarMinStorage_VPP1.csv
oHySEM/VPP1/oH_Data_VarPositionConsumption_VPP1.csv
oHySEM/VPP1/oH_Data_VarPositionGeneration_VPP1.csv
oHySEM/VPP1/oH_Data_VarPositionOutflows_VPP1.csv
oHySEM/VPP1/oH_Dict_AreaToRegion_VPP1.csv
oHySEM/VPP1/oH_Dict_Area_VPP1.csv
oHySEM/VPP1/oH_Dict_Circuit_VPP1.csv
oHySEM/VPP1/oH_Dict_ElectricityGeneration_VPP1.csv
oHySEM/VPP1/oH_Dict_HydrogenGeneration_VPP1.csv
ohysem-1.0.7.dist-info/entry_points.txt
ohysem-1.0.7.dist-info/LICENSE
ohysem-1.0.7.dist-info/WHEEL
ohysem-1.0.7.dist-info/METADATA
ohysem-1.0.7.dist-info/RECORD
