Metadata-Version: 2.3
Name: oHySEM
Version: 1.0.7
Summary: Optimized Hybrid Systems for Energy and Market management (oHySEM)
Home-page: https://ohysem.readthedocs.io/en/latest/index.html
Author: IIT-EnergySystemModels
Author-email: andres.ramos@comillas.edu
Requires-Python: >=3.11
Classifier: Development Status :: 5 - Production/Stable
Classifier: Intended Audience :: Science/Research
Classifier: License :: OSI Approved :: GNU General Public License v3 or later (GPLv3+)
Classifier: Operating System :: OS Independent
Classifier: Programming Language :: Python :: 3.11
Requires-Dist: pyomo>=6.8.0
Requires-Dist: matplotlib>=3.3.4
Requires-Dist: numpy>=1.20.1
Requires-Dist: pandas>=1.2.3
Requires-Dist: plotly>=5.7.0
Requires-Dist: colour>=0.1.5
Requires-Dist: altair>=5.0.0
Requires-Dist: psutil>=5.8.0
Requires-Dist: jsonschema>=4.16.0
Requires-Dist: streamlit>=1.38.0
Requires-Dist: networkx>=3.3
